factorial_t3sting/__init__.py
factorial_t3sting/app.py
factorial_t3sting/factorial.py
factorial_t3sting-0.1.0.dist-info/METADATA
factorial_t3sting-0.1.0.dist-info/WHEEL
factorial_t3sting-0.1.0.dist-info/RECORD
